LICENSE
README.md
pyproject.toml
src/__init__.py
src/fdiff/dataloaders/__init__.py
src/fdiff/dataloaders/datamodules.py
src/fdiff/models/__init__.py
src/fdiff/models/score_models.py
src/fdiff/models/transformer.py
src/fdiff/sampling/__init__.py
src/fdiff/sampling/metrics.py
src/fdiff/sampling/sampler.py
src/fdiff/schedulers/sde.py
src/fdiff/utils/__init__.py
src/fdiff/utils/callbacks.py
src/fdiff/utils/dataclasses.py
src/fdiff/utils/extraction.py
src/fdiff/utils/fourier.py
src/fdiff/utils/losses.py
src/fdiff/utils/preprocessing.py
src/fdiff/utils/tensors.py
src/fdiff/utils/wandb.py
src/fdiff/utils/wasserstein.py
src/freqdiff.egg-info/PKG-INFO
src/freqdiff.egg-info/SOURCES.txt
src/freqdiff.egg-info/dependency_links.txt
src/freqdiff.egg-info/requires.txt
src/freqdiff.egg-info/top_level.txt
tests/test_datamodules.py
tests/test_hydra_configs.py
tests/test_metrics.py
tests/test_sampling.py
tests/test_schedulers.py
tests/test_score_models.py
tests/test_transformer.py
tests/test_utils.py