Metadata-Version: 2.1
Name: freqdiff
Version: 0.1.0
Summary: Time series diffusion in the frequency domain.
Author-email: Jonathan Crabbé <jonathan.cr1302@gmail.com>, Nicolas Huynh <nicolas.huynh99@gmail.com>
Maintainer-email: Jonathan Crabbé <jonathan.cr1302@gmail.com>
License: MIT License
Project-URL: Homepage, https://github.com/JonathanCrabbe/FourierDiffusion/
Project-URL: Source, https://github.com/JonathanCrabbe/FourierDiffusion/
Keywords: diffusion,time,series,fourier,frequency,generative,machine,learning,ai
Classifier: Development Status :: 3 - Alpha
Classifier: Intended Audience :: Science/Research
Classifier: Topic :: Scientific/Engineering :: Artificial Intelligence
Classifier: License :: OSI Approved :: MIT License
Classifier: Programming Language :: Python :: 3.10
Requires-Python: >=3.10
License-File: LICENSE
Requires-Dist: torch
Requires-Dist: torchvision
Requires-Dist: torchaudio
Requires-Dist: lightning
Requires-Dist: kaggle
Requires-Dist: seaborn
Requires-Dist: pandas
Requires-Dist: diffusers[torch]
Requires-Dist: transformers
Requires-Dist: ipython
Requires-Dist: hydra-core
Requires-Dist: wandb
Requires-Dist: POT
Requires-Dist: tables
Requires-Dist: einops
Requires-Dist: SciencePlots
Provides-Extra: test
Requires-Dist: pytest; extra == "test"
Requires-Dist: coverage; extra == "test"
Requires-Dist: mypy; extra == "test"
Requires-Dist: black; extra == "test"
Requires-Dist: pytest-cov; extra == "test"
Requires-Dist: pytest-mypy; extra == "test"
Requires-Dist: pytest-black; extra == "test"
Requires-Dist: pytest-isort; extra == "test"
Requires-Dist: pytest-flakes; extra == "test"
Requires-Dist: pre-commit; extra == "test"
